LICENSE.md
MANIFEST.in
README.rst
pyproject.toml
requirements.core.txt
setup.py
core_dashboard_registry_app/__init__.py
core_dashboard_registry_app/admin.py
core_dashboard_registry_app/constants.py
core_dashboard_registry_app/menus.py
core_dashboard_registry_app/settings.py
core_dashboard_registry_app/urls.py
core_dashboard_registry_app.egg-info/PKG-INFO
core_dashboard_registry_app.egg-info/SOURCES.txt
core_dashboard_registry_app.egg-info/dependency_links.txt
core_dashboard_registry_app.egg-info/requires.txt
core_dashboard_registry_app.egg-info/top_level.txt
core_dashboard_registry_app/static/core_dashboard_registry_app/user/css/home.css
core_dashboard_registry_app/static/core_dashboard_registry_app/user/css/list/records.css
core_dashboard_registry_app/static/core_dashboard_registry_app/user/js/get_url.js
core_dashboard_registry_app/static/core_dashboard_registry_app/user/js/get_url.raw.js
core_dashboard_registry_app/static/core_dashboard_registry_app/user/js/record_registry.js
core_dashboard_registry_app/static/core_dashboard_registry_app/user/js/record_registry.raw.js
core_dashboard_registry_app/static/core_dashboard_registry_app/user/js/list/open_form.raw.js
core_dashboard_registry_app/static/core_dashboard_registry_app/user/js/list/publish.js
core_dashboard_registry_app/static/core_dashboard_registry_app/user/js/list/publish.raw.js
core_dashboard_registry_app/static/core_dashboard_registry_app/user/js/list/records.js
core_dashboard_registry_app/static/core_dashboard_registry_app/user/js/list/records.raw.js
core_dashboard_registry_app/templates/core_dashboard_common_app/my_dashboard.html
core_dashboard_registry_app/templates/core_dashboard_common_app/list/my_dashboard_my_forms_table.html
core_dashboard_registry_app/templates/core_dashboard_common_app/list/my_dashboard_my_records_table.html
core_dashboard_registry_app/templates/core_dashboard_common_app/list/my_dashboard_my_records_table_pagination.html
core_dashboard_registry_app/templates/core_dashboard_registry_app/home.html
core_dashboard_registry_app/templates/core_dashboard_registry_app/list/my_dashboard_my_forms_table.html
core_dashboard_registry_app/templates/core_dashboard_registry_app/list/my_dashboard_my_forms_table_pagination.html
